<?xml version="1.0" encoding="UTF-8"?>
<?xml-stylesheet type="text/xsl" href="admin-user.xsl"?>
<user-management>
    <user>
        <no>1</no>
        <image>user1.jpg</image>
        <email>john.doe@example.com</email>
        <name>John Doe</name>
    </user>
    <user>
        <no>2</no>
        <image>jane.smith.jpg</image>
        <email>jane.smith@example.com</email>
        <name>Jane Smith</name>
    </user>
    <user>
        <no>3</no>
        <image>mike.johnson.jpg</image>
        <email>mike.johnson@example.com</email>
        <name>Mike Johnson</name>
    </user>
</user-management>
